README
setup.py
maxcul/__init__.py
maxcul/communication.py
maxcul/exceptions.py
maxcul/messages.py
maxcul/signals.py
maxcul.egg-info/PKG-INFO
maxcul.egg-info/SOURCES.txt
maxcul.egg-info/dependency_links.txt
maxcul.egg-info/requires.txt
maxcul.egg-info/top_level.txt