Metadata-Version: 1.1
Name: maxcul
Version: 0.1.1
Summary: Access with Python MAX! Devices over a CUL Stick
Home-page: https://github.com/karlTGA/MaxCul-Python
Author: Markus Ullmann, Karl Wolffgang
Author-email: karlwolffgang@googlemail.com
License: BSD License
Platform: any
Classifier: Programming Language :: Python
Classifier: Development Status :: 4 - Beta
Classifier: Natural Language :: English
Classifier: Environment :: Console
Classifier: Intended Audience :: Developers
Classifier: License :: OSI Approved :: BSD License
Classifier: Operating System :: OS Independent
Classifier: Topic :: Software Development :: Libraries :: Python Modules
Classifier: Topic :: Home Automation
